dougdougmugmug/__init__.py
dougdougmugmug/cli.py
dougdougmugmug-0.1.1.dist-info/METADATA
dougdougmugmug-0.1.1.dist-info/WHEEL
dougdougmugmug-0.1.1.dist-info/entry_points.txt
dougdougmugmug-0.1.1.dist-info/top_level.txt
dougdougmugmug-0.1.1.dist-info/RECORD
