Metadata-Version: 2.4
Name: dougdougmugmug
Version: 0.1.1
Summary: Print DougDoug MugMug ASCII art
License: MIT
Requires-Python: >=3.8
Requires-Dist: rich
